{
  "P01": {
    "persona_id": "P01",
    "days": [
      {
        "day": 1,
        "date": "2025-01-03",
        "weekday": "星期五",
        "mood": "担心服务器的病，工作时心不在焉",
        "weather": "阴天，有微风，16℃",
        "原子层": [
          {
            "start": "09:00",
            "end": "09:01",
            "location": "卧室",
            "action": "床头柜上的手机屏幕亮起，伸手拿起手机"
          },
          {
            "start": "09:01",
            "end": "09:02",
            "location": "卧室",
            "action": "侧躺，拇指滑动屏幕关闭闹钟"
          },
          {
            "start": "09:02",
            "end": "09:05",
            "location": "卧室",
            "action": "侧躺，拇指在屏幕上滑动浏览"
          },
          {
            "start": "09:05",
            "end": "09:06",
            "location": "卧室",
            "action": "橘猫跳上床，从床尾走向枕头边"
          },
          {
            "start": "09:06",
            "end": "09:07",
            "location": "卧室",
            "action": "伸出左手抚摸猫的头部和背部"
          },
          {
            "start": "09:07",
            "end": "09:08",
            "location": "卧室",
            "action": "坐起身，掀开被子"
          },
          {
            "start": "09:08",
            "end": "09:09",
            "location": "卧室",
            "action": "双腿移下床，双脚穿进拖鞋"
          },
          {
            "start": "09:09",
            "end": "09:10",
            "location": "卧室",
            "action": "站起来，走向卧室门口"
          },
          {
            "start": "09:10",
            "end": "09:11",
            "location": "客厅",
            "action": "经过客厅，走进卫生间"
          },
          {
            "start": "09:11",
            "end": "09:12",
            "location": "卫生间",
            "action": "关上门，走到马桶前，褪下裤子坐下"
          },
          {
            "start": "09:12",
            "end": "09:18",
            "location": "卫生间",
            "action": "坐在马桶上，低头看手机，拇指滑动"
          },
          {
            "start": "09:18",
            "end": "09:19",
            "location": "卫生间",
            "action": "站起身，按下冲水按钮，提上裤子"
          },
          {
            "start": "09:19",
            "end": "09:20",
            "location": "卫生间",
            "action": "走到洗手池前，按压洗手液搓手，打开水龙头冲洗"
          },
          {
            "start": "09:20",
            "end": "09:21",
            "location": "卫生间",
            "action": "从牙杯架取下牙刷，挤上牙膏"
          },
          {
            "start": "09:21",
            "end": "09:23",
            "location": "卫生间",
            "action": "把牙刷放进嘴里，来回刷牙"
          },
          {
            "start": "09:23",
            "end": "09:24",
            "location": "卫生间",
            "action": "拿起牙杯接水漱口，吐水"
          },
          {
            "start": "09:24",
            "end": "09:25",
            "location": "卫生间",
            "action": "打开水龙头，双手接水扑到脸上"
          },
          {
            "start": "09:25",
            "end": "09:26",
            "location": "卫生间",
            "action": "用毛巾擦干脸和手"
          },
          {
            "start": "09:26",
            "end": "09:27",
            "location": "卫生间",
            "action": "打开门，走出卫生间"
          },
          {
            "start": "09:27",
            "end": "09:28",
            "location": "厨房",
            "action": "走进厨房，打开上方橱柜门，拿出猫粮袋"
          },
          {
            "start": "09:28",
            "end": "09:29",
            "location": "厨房",
            "action": "撕开猫粮袋封口，向地上猫碗里倒猫粮"
          },
          {
            "start": "09:29",
            "end": "09:30",
            "location": "厨房",
            "action": "封好猫粮袋，放回橱柜"
          },
          {
            "start": "09:30",
            "end": "09:31",
            "location": "厨房",
            "action": "弯腰端起地上的水碗，走到水槽边倒掉旧水"
          },
          {
            "start": "09:31",
            "end": "09:32",
            "location": "厨房",
            "action": "打开水龙头冲洗水碗，接上干净水"
          },
          {
            "start": "09:32",
            "end": "09:33",
            "location": "厨房",
            "action": "端着水碗走回原处放下"
          },
          {
            "start": "09:33",
            "end": "09:34",
            "location": "厨房",
            "action": "橘猫从客厅跑进厨房，走向角落的猫砂盆"
          },
          {
            "start": "09:34",
            "end": "09:35",
            "location": "厨房",
            "action": "猫跳进猫砂盆，蹲下片刻，跳出跑开"
          },
          {
            "start": "09:35",
            "end": "09:36",
            "location": "厨房",
            "action": "人走到猫砂盆前蹲下"
          },
          {
            "start": "09:36",
            "end": "09:37",
            "location": "厨房",
            "action": "伸手拿起猫砂铲，铲起几个小结团"
          },
          {
            "start": "09:37",
            "end": "09:38",
            "location": "厨房",
            "action": "用猫砂铲托着结团，走到垃圾桶前倒入"
          },
          {
            "start": "09:38",
            "end": "09:39",
            "location": "厨房",
            "action": "回到猫砂盆边，用铲子把猫砂铺平"
          },
          {
            "start": "09:39",
            "end": "09:40",
            "location": "厨房",
            "action": "走到水槽旁，打开水龙头洗手"
          },
          {
            "start": "09:40",
            "end": "09:41",
            "location": "厨房",
            "action": "用擦手布擦干双手，走出厨房"
          },
          {
            "start": "09:41",
            "end": "09:42",
            "location": "卧室",
            "action": "走进卧室，从衣架上取下外套穿上"
          },
          {
            "start": "09:42",
            "end": "09:43",
            "location": "客厅",
            "action": "走到沙发旁，弯腰伸手摸了一下猫头"
          },
          {
            "start": "09:43",
            "end": "09:44",
            "location": "客厅",
            "action": "拿起沙发上的双肩包，背到肩上"
          },
          {
            "start": "09:44",
            "end": "09:45",
            "location": "客厅",
            "action": "走到门口，坐在鞋凳上穿运动鞋"
          },
          {
            "start": "09:45",
            "end": "09:46",
            "location": "门口",
            "action": "站起身开门，走出门，回头关门"
          },
          {
            "start": "09:46",
            "end": "09:49",
            "location": "小区",
            "action": "下楼，经过小区花园走向大门"
          },
          {
            "start": "09:49",
            "end": "09:50",
            "location": "小区大门",
            "action": "刷门禁卡通过闸机，走出小区"
          },
          {
            "start": "09:50",
            "end": "09:56",
            "location": "街道",
            "action": "沿人行道行走，等红灯，过马路"
          },
          {
            "start": "09:56",
            "end": "09:57",
            "location": "地铁站入口",
            "action": "走进地铁站口，下楼梯进入站厅"
          },
          {
            "start": "09:57",
            "end": "09:58",
            "location": "地铁站厅",
            "action": "过安检，刷卡通过闸机"
          },
          {
            "start": "09:58",
            "end": "09:59",
            "location": "地铁站",
            "action": "乘扶梯下到站台"
          },
          {
            "start": "09:59",
            "end": "10:01",
            "location": "地铁站台",
            "action": "站在黄线后，面朝轨道方向等待"
          },
          {
            "start": "10:01",
            "end": "10:02",
            "location": "地铁站台",
            "action": "列车进站停稳，车门打开，走进车厢"
          },
          {
            "start": "10:02",
            "end": "10:20",
            "location": "地铁车厢",
            "action": "手抓吊环站立，周围站满乘客"
          },
          {
            "start": "10:20",
            "end": "10:21",
            "location": "地铁车厢",
            "action": "列车减速到站，松开扶手走出车厢"
          },
          {
            "start": "10:21",
            "end": "10:22",
            "location": "地铁站",
            "action": "跟随人流乘扶梯上行出站"
          },
          {
            "start": "10:22",
            "end": "10:23",
            "location": "地铁站厅",
            "action": "刷卡通过出站闸机，走向出口"
          },
          {
            "start": "10:23",
            "end": "10:28",
            "location": "街道",
            "action": "走出地铁口，沿街走向公司大楼"
          },
          {
            "start": "10:28",
            "end": "10:29",
            "location": "公司大楼大厅",
            "action": "进入大楼，走向电梯间按下上行按钮"
          },
          {
            "start": "10:29",
            "end": "10:30",
            "location": "电梯",
            "action": "走进电梯，按下楼层按钮"
          },
          {
            "start": "10:30",
            "end": "10:31",
            "location": "公司前台",
            "action": "出电梯，走向公司玻璃门，抬手打卡"
          },
          {
            "start": "10:31",
            "end": "10:32",
            "location": "公司工位",
            "action": "走到工位，放下双肩包"
          },
          {
            "start": "10:32",
            "end": "10:33",
            "location": "公司工位",
            "action": "从包里取出笔记本电脑，放到桌上打开"
          },
          {
            "start": "10:33",
            "end": "10:34",
            "location": "公司工位",
            "action": "按下电源键，拉出椅子坐下"
          },
          {
            "start": "10:34",
            "end": "10:35",
            "location": "公司工位",
            "action": "面对屏幕等待系统启动"
          },
          {
            "start": "10:35",
            "end": "10:36",
            "location": "公司工位",
            "action": "双手放在键盘上，输入密码"
          },
          {
            "start": "10:36",
            "end": "11:10",
            "location": "公司工位",
            "action": "坐在工位，面对电脑屏幕，敲键盘移动鼠标"
          },
          {
            "start": "11:10",
            "end": "11:11",
            "location": "公司工位",
            "action": "从工位起身，拿起桌上的水杯"
          },
          {
            "start": "11:11",
            "end": "11:12",
            "location": "公司茶水间",
            "action": "走向茶水间"
          },
          {
            "start": "11:12",
            "end": "11:14",
            "location": "公司茶水间",
            "action": "拿起咖啡壶，往杯子里倒咖啡"
          },
          {
            "start": "11:14",
            "end": "11:15",
            "location": "公司工位",
            "action": "端着杯子回到工位坐下"
          },
          {
            "start": "11:15",
            "end": "12:00",
            "location": "公司工位",
            "action": "面对电脑屏幕，继续敲键盘移动鼠标"
          },
          {
            "start": "12:00",
            "end": "12:02",
            "location": "公司工位",
            "action": "拿起手机，拇指在屏幕上点击"
          },
          {
            "start": "12:02",
            "end": "12:25",
            "location": "公司工位",
            "action": "面对屏幕，偶尔点击鼠标"
          },
          {
            "start": "12:25",
            "end": "12:26",
            "location": "公司工位",
            "action": "手机屏幕亮起，拿起手机看一眼，起身"
          },
          {
            "start": "12:26",
            "end": "12:28",
            "location": "公司电梯口",
            "action": "走向电梯口，看到戴头盔的人递来袋子，双手接过"
          },
          {
            "start": "12:28",
            "end": "12:29",
            "location": "公司工位",
            "action": "拎着外卖袋走回工位坐下"
          },
          {
            "start": "12:29",
            "end": "12:30",
            "location": "公司工位",
            "action": "解开塑料袋，取出外卖盒，打开盖子"
          },
          {
            "start": "12:30",
            "end": "12:31",
            "location": "公司工位",
            "action": "拿起筷子，夹出盒里的绿色香菜叶放到纸巾上"
          },
          {
            "start": "12:31",
            "end": "12:45",
            "location": "公司工位",
            "action": "用筷子夹饭菜送进嘴里，咀嚼吞咽"
          },
          {
            "start": "12:45",
            "end": "12:46",
            "location": "公司工位",
            "action": "放下筷子，合上外卖盒盖"
          },
          {
            "start": "12:46",
            "end": "12:47",
            "location": "公司工位",
            "action": "拎起外卖垃圾，起身走向垃圾桶丢弃"
          },
          {
            "start": "12:47",
            "end": "12:49",
            "location": "公司卫生间",
            "action": "走进卫生间，打开水龙头洗手，用纸巾擦干"
          },
          {
            "start": "12:49",
            "end": "12:50",
            "location": "公司工位",
            "action": "回到工位坐下"
          },
          {
            "start": "12:50",
            "end": "13:00",
            "location": "公司工位",
            "action": "左手拿手机，拇指滑动屏幕"
          },
          {
            "start": "13:00",
            "end": "14:00",
            "location": "公司工位",
            "action": "面对电脑屏幕，双手敲键盘点击鼠标"
          },
          {
            "start": "14:00",
            "end": "14:01",
            "location": "公司工位",
            "action": "起身拿起杯子，走向茶水间"
          },
          {
            "start": "14:01",
            "end": "14:03",
            "location": "公司茶水间",
            "action": "走到咖啡机前，按下按钮接咖啡"
          },
          {
            "start": "14:03",
            "end": "14:04",
            "location": "公司工位",
            "action": "端着咖啡回到工位坐下"
          },
          {
            "start": "14:04",
            "end": "14:30",
            "location": "公司工位",
            "action": "左手拿着手机拇指滑动，右手偶尔点鼠标"
          },
          {
            "start": "14:30",
            "end": "14:31",
            "location": "公司工位",
            "action": "放下手机，双手放上键盘"
          },
          {
            "start": "14:31",
            "end": "14:40",
            "location": "公司工位",
            "action": "快速敲击键盘，眼睛紧盯屏幕"
          },
          {
            "start": "14:40",
            "end": "14:41",
            "location": "公司工位",
            "action": "停止敲键盘，右手托腮，盯着屏幕"
          },
          {
            "start": "14:41",
            "end": "14:50",
            "location": "公司工位",
            "action": "右手滚动鼠标滚轮，眼睛看屏幕"
          },
          {
            "start": "14:50",
            "end": "15:00",
            "location": "公司工位",
            "action": "右手托腮，手指在鼠标滚轮上缓慢滑动"
          },
          {
            "start": "15:00",
            "end": "15:02",
            "location": "公司工位",
            "action": "从工位起身，走向卫生间"
          },
          {
            "start": "15:02",
            "end": "15:06",
            "location": "公司卫生间",
            "action": "走进隔间小便，出来洗手，照镜子"
          },
          {
            "start": "15:06",
            "end": "15:07",
            "location": "公司工位",
            "action": "回到工位坐下"
          },
          {
            "start": "15:07",
            "end": "16:00",
            "location": "公司工位",
            "action": "面对屏幕，双手敲键盘移动鼠标"
          },
          {
            "start": "16:00",
            "end": "16:01",
            "location": "公司工位",
            "action": "起身拿起笔记本和笔，走向会议室"
          },
          {
            "start": "16:01",
            "end": "16:02",
            "location": "公司会议室",
            "action": "走进会议室，拉开椅子坐下"
          },
          {
            "start": "16:02",
            "end": "16:30",
            "location": "公司会议室",
            "action": "面对前方投影幕布，偶尔低头在笔记本上写字"
          },
          {
            "start": "16:30",
            "end": "16:31",
            "location": "公司会议室",
            "action": "合上笔记本，起身推开椅子，走出会议室"
          },
          {
            "start": "16:31",
            "end": "17:30",
            "location": "公司工位",
            "action": "回到工位坐下，面对屏幕继续敲键盘"
          },
          {
            "start": "17:30",
            "end": "17:32",
            "location": "公司工位",
            "action": "拿起手机，拇指点击屏幕"
          },
          {
            "start": "17:32",
            "end": "18:00",
            "location": "公司工位",
            "action": "面对电脑屏幕敲键盘，偶尔看手机"
          },
          {
            "start": "18:00",
            "end": "18:01",
            "location": "公司工位",
            "action": "手机屏幕亮起，看一眼，起身"
          },
          {
            "start": "18:01",
            "end": "18:03",
            "location": "公司电梯口",
            "action": "走到电梯口，从外卖员手中接过袋子"
          },
          {
            "start": "18:03",
            "end": "18:04",
            "location": "公司工位",
            "action": "拎袋子回工位坐下，取出饭盒打开"
          },
          {
            "start": "18:04",
            "end": "18:20",
            "location": "公司工位",
            "action": "用筷子夹饭菜送进嘴里咀嚼"
          },
          {
            "start": "18:20",
            "end": "18:22",
            "location": "公司工位",
            "action": "收拾饭盒和一次性餐具，起身扔进垃圾桶"
          },
          {
            "start": "18:22",
            "end": "18:24",
            "location": "公司卫生间",
            "action": "走进卫生间洗手，擦干"
          },
          {
            "start": "18:24",
            "end": "18:30",
            "location": "公司工位",
            "action": "回到工位坐下，拿起手机拇指滑动"
          },
          {
            "start": "18:30",
            "end": "20:00",
            "location": "公司工位",
            "action": "面对电脑屏幕，双手敲键盘移动鼠标"
          },
          {
            "start": "20:00",
            "end": "20:01",
            "location": "公司工位",
            "action": "起身拿起水杯，走向茶水间"
          },
          {
            "start": "20:01",
            "end": "20:03",
            "location": "公司茶水间",
            "action": "在饮水机前接满温水"
          },
          {
            "start": "20:03",
            "end": "20:04",
            "location": "公司工位",
            "action": "端着杯子回到工位坐下"
          },
          {
            "start": "20:04",
            "end": "21:45",
            "location": "公司工位",
            "action": "面对屏幕继续敲键盘点鼠标"
          },
          {
            "start": "21:45",
            "end": "21:50",
            "location": "公司工位",
            "action": "合上笔记本电脑，收拾桌面物品装进背包"
          },
          {
            "start": "21:50",
            "end": "21:52",
            "location": "公司前台",
            "action": "起身离开工位，走到公司门口打卡，出门"
          },
          {
            "start": "21:52",
            "end": "22:00",
            "location": "街道",
            "action": "走出大楼，沿街走向地铁站"
          },
          {
            "start": "22:00",
            "end": "22:18",
            "location": "地铁车厢",
            "action": "进站刷卡，乘坐地铁，手抓扶手站立"
          },
          {
            "start": "22:18",
            "end": "22:20",
            "location": "街道",
            "action": "下地铁，刷卡出站，走回小区"
          },
          {
            "start": "22:20",
            "end": "22:22",
            "location": "楼道",
            "action": "进入单元门，按电梯上楼"
          },
          {
            "start": "22:22",
            "end": "22:23",
            "location": "家门口",
            "action": "走到家门前，掏钥匙开门，推门进入"
          },
          {
            "start": "22:23",
            "end": "22:24",
            "location": "客厅",
            "action": "放下背包，换上拖鞋"
          },
          {
            "start": "22:24",
            "end": "22:25",
            "location": "客厅",
            "action": "橘猫从沙发跳下走来蹭腿，弯腰伸手摸猫"
          },
          {
            "start": "22:25",
            "end": "22:26",
            "location": "厨房",
            "action": "走向厨房，蹲下查看地上的猫碗"
          },
          {
            "start": "22:26",
            "end": "22:27",
            "location": "厨房",
            "action": "从橱柜拿出猫粮袋，往碗里添猫粮"
          },
          {
            "start": "22:27",
            "end": "22:28",
            "location": "厨房",
            "action": "端起水碗倒掉旧水，冲洗后接干净水放回"
          },
          {
            "start": "22:28",
            "end": "22:30",
            "location": "厨房",
            "action": "走到猫砂盆前蹲下，铲出几个小结团倒入垃圾桶"
          },
          {
            "start": "22:30",
            "end": "22:32",
            "location": "客厅",
            "action": "走到沙发前坐下，拿起手机拇指滑动"
          },
          {
            "start": "22:32",
            "end": "22:50",
            "location": "客厅",
            "action": "背靠沙发看手机，猫跳上沙发蜷在身旁"
          },
          {
            "start": "22:50",
            "end": "22:51",
            "location": "客厅",
            "action": "放下手机，从沙发起身走向卫生间"
          },
          {
            "start": "22:51",
            "end": "22:52",
            "location": "卫生间",
            "action": "走进卫生间，脱下上衣和裤子"
          },
          {
            "start": "22:52",
            "end": "23:05",
            "location": "卫生间",
            "action": "站在花洒下冲洗身体，涂抹沐浴露"
          },
          {
            "start": "23:05",
            "end": "23:06",
            "location": "卫生间",
            "action": "关掉花洒，用浴巾擦干身体"
          },
          {
            "start": "23:06",
            "end": "23:07",
            "location": "卫生间",
            "action": "穿上干净内裤和睡衣"
          },
          {
            "start": "23:07",
            "end": "23:10",
            "location": "卫生间",
            "action": "拿起牙刷挤牙膏，刷完牙漱口"
          },
          {
            "start": "23:10",
            "end": "23:11",
            "location": "卧室",
            "action": "走出卫生间，进入卧室"
          },
          {
            "start": "23:11",
            "end": "23:12",
            "location": "卧室",
            "action": "掀开被子，躺到床上，拉好被子"
          },
          {
            "start": "23:12",
            "end": "23:30",
            "location": "卧室",
            "action": "背靠床头，双手拿手机拇指滑动屏幕"
          },
          {
            "start": "23:30",
            "end": "23:31",
            "location": "卧室",
            "action": "放下手机到床头柜，伸手关闭台灯，房间变暗"
          }
        ],
        "事件层": [
          {
            "time_range": "09:00-09:26",
            "event": "被闹钟叫醒，躺着刷了会儿手机。橘猫跳上床蹭我，摸了几下后起床，上厕所顺便看了会儿技术新闻，然后刷牙洗脸。"
          },
          {
            "time_range": "09:27-09:40",
            "event": "橘猫跑进厨房催饭，给它倒猫粮、换干净水。刚换完它就去用猫砂盆，赶紧跟着铲了结团，收拾完洗手。"
          },
          {
            "time_range": "09:41-10:30",
            "event": "穿上外套背上包出门，摸了下猫头道别。走路去地铁站，站了一路，有点挤，出站后走到公司楼下刷卡进楼。"
          },
          {
            "time_range": "10:31-12:00",
            "event": "到工位坐下开电脑，开始干活。中间去茶水间倒了杯咖啡提神。但因为一直惦记服务器生病的事，心不在焉，效率不太高。"
          },
          {
            "time_range": "12:00-12:25",
            "event": "坐在工位前心不在焉地摸鱼，因为担心服务器的事，只是偶尔点下鼠标应付屏幕，完全提不起精神干活。"
          },
          {
            "time_range": "12:25-12:50",
            "event": "手机亮屏提醒外卖到了，起身去电梯口接过袋子。回到座位打开饭盒，习惯性地把香菜一片片挑出来放在纸巾上，然后慢慢吃完，收拾好垃圾去洗了手。"
          },
          {
            "time_range": "12:50-14:30",
            "event": "饭后拿着手机刷了一会儿，下午继续面对电脑但效率很低，一边敲键盘一边忍不住滑手机。中途去茶水间接了杯咖啡，回来还是左手刷手机、右手偶尔点鼠标，整个人很飘。"
          },
          {
            "time_range": "14:30-15:00",
            "event": "突然放下手机快速敲了一阵键盘，像是想补救一下进度，但没坚持多久就托着腮发呆，手指在鼠标滚轮上慢慢滑，脑子里还是绕不开服务器的问题。"
          },
          {
            "time_range": "15:00-15:07",
            "event": "去了一趟卫生间，洗了手照了镜子，很快又回到工位。"
          },
          {
            "time_range": "15:07-16:00",
            "event": "坐在工位上敲代码，但心里一直担心服务器的毛病，有点心不在焉。"
          },
          {
            "time_range": "16:00-16:31",
            "event": "拿着笔记本去会议室参加了一个半小时的分享或例会，边听边记笔记。"
          },
          {
            "time_range": "16:31-18:00",
            "event": "开完会回到工位继续干活，中间拿起手机刷了一下，然后一边敲键盘一边偶尔看手机，状态还是被服务器的事分心。"
          },
          {
            "time_range": "18:00-18:24",
            "event": "取外卖回工位吃晚饭。心里一直惦记着那台生病的服务器，吃饭也没什么滋味，机械地嚼完收拾掉。去卫生间洗了手。"
          },
          {
            "time_range": "18:24-18:30",
            "event": "饭后坐下来刷了会儿手机，想看看有没有服务器恢复的消息，但心里乱糟糟的，只是拇指在屏幕上无意义地滑动。"
          },
          {
            "time_range": "18:30-21:45",
            "event": "硬撑着继续加班，对着屏幕敲键盘改配置。中间八点去茶水间接了杯温水缓了缓，然后回来一直搞到快十点。因为担心服务器状态，全程都有点心不在焉。"
          },
          {
            "time_range": "21:00-21:45",
            "event": "在公司加班到快十点，心里一直惦记着服务器的毛病，对着屏幕敲键盘却有点心不在焉。"
          },
          {
            "time_range": "21:45-22:22",
            "event": "合上电脑收拾东西，打卡离开公司。走出大楼沿街去地铁站，坐地铁回家，路上还在琢磨服务器的事儿。"
          },
          {
            "time_range": "22:22-23:10",
            "event": "到家放下背包换鞋，橘猫立刻跑过来蹭腿。给它加了猫粮换了干净水，又把猫砂盆里的结团铲掉。忙完猫的事，自己也去洗了个热水澡，刷完牙换上睡衣，整个人终于从加班的状态里松下来一点。"
          },
          {
            "time_range": "23:10-23:31",
            "event": "躺到床上，背靠床头刷了会儿手机，像是想把白天没顾上的信息补回来。最后放下手机关掉台灯，房间暗下来，结束这疲惫的一天。"
          }
        ],
        "每日总结": "今天整天因为一台生病的服务器而心神不宁，工作几乎全被焦虑拖慢，多次刷手机也是在等恢复消息；加班到深夜仍无结果，疲惫且悬着一颗心。橘猫的照料节奏正常，香菜照例挑出，没有明显习惯变化，但心里一直压着未解决的服务器问题，回家后才稍松一口气。"
      }
    ]
  }
}